Workbook

Sheet Channel_Summary
A3: Row Labels | B3: Sum of Gross_Revenue | C3: Sum of Net_Sales | D3: Sum of Contribution_Margin
A4: Marketplace | B4: 406000 | C4: 391100 | D4: 98740
A5: Retail Store | B5: 240000 | C5: 234500 | D5: 97271
A6: Shopify | B6: 420000 | C6: 397900 | D6: 141885
A7: Grand Total | B7: 1066000 | C7: 1023500 | D7: 337896

Sheet Sales_Data
A1: Transaction_ID | B1: Date | C1: Channel | D1: Category | E1: Units_Sold | F1: Gross_Revenue | G1: Discounts | H1: COGS | I1: Shipping_Cost | J1: Gateway_Commission | K1: Net_Sales | L1: Contribution_Margin
A2: TXN1001 | B2: 46296 | C2: Shopify | D2: Sneakers | E2: 1 | F2: 12000 | G2: 1000 | H2: 7000 | I2: 250 | J2: 360 | K2: =F2-G2 -> 11000 | L2: =K2-H2-I2-J2 -> 3390
A3: TXN1002 | B3: 46296 | C3: Marketplace | D3: Apparel | E3: 2 | F3: 4500 | G3: 200 | H3: 2200 | I3: 150 | J3: 675 | K3: =F3-G3 -> 4300 | L3: =K3-H3-I3-J3 -> 1275
A4: TXN1003 | B4: 46297 | C4: Retail Store | D4: Accessories | E4: 1 | F4: 2500 | G4: 0 | H4: 1000 | I4: 0 | J4: 50 | K4: =F4-G4 -> 2500 | L4: =K4-H4-I4-J4 -> 1450
A5: TXN1004 | B5: 46297 | C5: Shopify | D5: Sneakers | E5: 1 | F5: 15000 | G5: 1500 | H5: 9000 | I5: 250 | J5: 450 | K5: =F5-G5 -> 13500 | L5: =K5-H5-I5-J5 -> 3800
A6: TXN1005 | B6: 46174 | C6: Shopify | D6: Accessories | E6: 1 | F6: 1500 | G6: 0 | H6: 620 | I6: 100 | J6: 45 | K6: =F6-G6 -> 1500 | L6: =K6-H6-I6-J6 -> 735
A7: TXN1006 | B7: 46174 | C7: Retail Store | D7: Sneakers | E7: 1 | F7: 18000 | G7: 0 | H7: 9945 | I7: 0 | J7: 360 | K7: =F7-G7 -> 18000 | L7: =K7-H7-I7-J7 -> 7695
A8: TXN1007 | B8: 46175 | C8: Marketplace | D8: Sneakers | E8: 2 | F8: 24000 | G8: 0 | H8: 13860 | I8: 400 | J8: 3600 | K8: =F8-G8 -> 24000 | L8: =K8-H8-I8-J8 -> 6140
A9: TXN1008 | B9: 46176 | C9: Marketplace | D9: Sneakers | E9: 1 | F9: 15000 | G9: 0 | H9: 8584 | I9: 200 | J9: 2250 | K9: =F9-G9 -> 15000 | L9: =K9-H9-I9-J9 -> 3966
A10: TXN1009 | B10: 46177 | C10: Shopify | D10: Accessories | E10: 1 | F10: 1000 | G10: 0 | H10: 423 | I10: 100 | J10: 30 | K10: =F10-G10 -> 1000 | L10: =K10-H10-I10-J10 -> 447
A11: TXN1010 | B11: 46178 | C11: Shopify | D11: Sneakers | E11: 1 | F11: 8000 | G11: 500 | H11: 4941 | I11: 250 | J11: 240 | K11: =F11-G11 -> 7500 | L11: =K11-H11-I11-J11 -> 2069
A12: TXN1011 | B12: 46179 | C12: Shopify | D12: Apparel | E12: 1 | F12: 3500 | G12: 0 | H12: 1712 | I12: 150 | J12: 105 | K12: =F12-G12 -> 3500 | L12: =K12-H12-I12-J12 -> 1533
A13: TXN1012 | B13: 46180 | C13: Retail Store | D13: Apparel | E13: 1 | F13: 3500 | G13: 0 | H13: 1430 | I13: 0 | J13: 70 | K13: =F13-G13 -> 3500 | L13: =K13-H13-I13-J13 -> 2000
... A100: TXN1099 | B100: 46270 | C100: Shopify | D100: Sneakers | E100: 1 | F100: 22000 | G100: 1500 | H100: 13140 | I100: 250 | J100: 615 | K100: =F100-G100 -> 20500 | L100: =K100-H100-I100-J100 -> 6495

Sheet Budget_Variance
A1: Channel | B1: Metric | C1: Budgeted_Target | D1: Actual_Performance | E1: Variance_Amount | F1: Variance_Percentage
A2: Shopify | B2: Net Sales | C2: 350000 | D2: =GETPIVOTDATA("Net_Sales", Channel_Summary!$A$3, "Channel", A2) -> 397900 | E2: =D2 - C2 -> 47900 | F2: =E2 / C2 -> 0.13685714
A3: Marketplace | B3: Net Sales | C3: 375000 | D3: =Channel_Summary!C4 -> 391100 | E3: =D3-C3 -> 16100 | F3: =(D3-C3)/C3 -> 0.042933333
A4: Retail Store | B4: Net Sales | C4: 220000 | D4: =Channel_Summary!C5 -> 234500 | E4: =D4-C4 -> 14500 | F4: =(D4-C4)/C4 -> 0.065909091
A5: Shopify | B5: COGS | C5: 200000 | D5: =SUMIF(Sales_Data!$C:$C, A5, Sales_Data!$H:$H) -> 233643 | E5: =C5-D5 -> -33643 | F5: =E5/C5 -> -0.168215
A6: Marketplace | B6: COGS | C6: 130000 | D6: =SUMIF(Sales_Data!$C:$C, A6, Sales_Data!$H:$H) -> 225475 | E6: =C6-D6 -> -95475 | F6: =E6/C6 -> -0.73442308
A7: Retail Store | B7: COGS | C7: 130000 | D7: =SUMIF(Sales_Data!$C:$C, A7, Sales_Data!$H:$H) -> 132489 | E7: =C7-D7 -> -2489 | F7: =E7/C7 -> -0.019146154
A8: Shopify | B8: Contribution Margin | C8: 130000 | D8: =GETPIVOTDATA("Contribution_Margin", Channel_Summary!$A$3, "Channel", "Shopify") -> 141885 | E8: =D8-C8 -> 11885 | F8: =E8/C8 -> 0.091423077
A9: Marketplace | B9: Contribution Margin | C9: 95000 | D9: =GETPIVOTDATA("Contribution_Margin", Channel_Summary!$A$3, "Channel", "Marketplace") -> 98740 | E9: =D9-C9 -> 3740 | F9: =E9/C9 -> 0.039368421
A10: Retail Store | B10: Contribution Margin | C10: 90000 | D10: =GETPIVOTDATA("Contribution_Margin", Channel_Summary!$A$3, "Channel", "Retail Store") -> 97271 | E10: =D10-C10 -> 7271 | F10: =E10/C10 -> 0.080788889

Sheet Management_Dashboard
B1: Multi-Channel D2C Executive Dashboard (June 2026 – October 2026) | F1: Total Net Sales | J1: Total Contribution Margin
B2: =Channel_Summary!B7 -> 1066000 | F2: =Channel_Summary!C7 -> 1023500 | J2: =Channel_Summary!D7 -> 337896

Sheet Settlement_Reconciliation
A1: D2C Cash Settlement & Payout Reconciliation (June – October 2026)
A3: Channel | B3: Actual Net Sales | C3: Gateway / Commission Fees (%) | D3: Deduction Amount | E3: COD Reserve Holdback | F3: Net Bank Payout
A4: Shopify | B4: =Channel_Summary!C6 -> 397900 | C4: 0.02 | D4: =B4*C4 -> 7958 | E4: 0 | F4: =B4-D4-E4 -> 389942
A5: Marketplace | B5: =Channel_Summary!C4 -> 391100 | C5: 0.15 | D5: =B5*C5 -> 58665 | E5: 35000 | F5: =B5-D5-E5 -> 297435
A6: Retail Store | B6: =Channel_Summary!C5 -> 234500 | C6: 0.01 | D6: =B6*C6 -> 2345 | E6: 0 | F6: =B6-D6-E6 -> 232155
A8: Total | B8: =SUM(B4:B6) -> 1023500 | D8: =SUM(D4:D6) -> 68968 | E8: =SUM(E4:E6) -> 35000 | F8: =SUM(F4:F6) -> 919532
